release.py
racket/__about__.py
racket/__init__.py
racket/bot.py
racket/context_menu.py
racket/interaction_history.py
racket/run_cog.py
racket/setup_logging.py
discord_racket-0.0.14.dist-info/METADATA
discord_racket-0.0.14.dist-info/WHEEL
discord_racket-0.0.14.dist-info/licenses/LICENSE
discord_racket-0.0.14.dist-info/RECORD
