Metadata-Version: 2.1
Name: discord-racket
Version: 0.0.14
Summary: Discord bot utility framework.
Project-URL: Homepage, https://github.com/burtonwilliamt/racket
Project-URL: Bug Tracker, https://github.com/burtonwilliamt/racket/issues
Author-email: William Burton <13026711+burtonwilliamt@users.noreply.github.com>
License-File: LICENSE
Classifier: License :: OSI Approved :: MIT License
Classifier: Operating System :: OS Independent
Classifier: Programming Language :: Python :: 3
Requires-Python: >=3.10
Requires-Dist: discord-py>=2.2.0
